keys/__init__.py
keys/private_key.pem
keys/public_key.pem
parser/__init__.py
parser/acfun.py
parser/base.py
parser/doupai.py
parser/douyin.py
parser/haokan.py
parser/huya.py
parser/kuaishou.py
parser/lishipin.py
parser/lvzhou.py
parser/meipai.py
parser/pipigaoxiao.py
parser/pipixia.py
parser/quanmin.py
parser/quanminkge.py
parser/redbook.py
parser/sixroom.py
parser/weibo.py
parser/weishi.py
parser/xigua.py
parser/xinpianchang.py
parser/zuiyou.py
utils/__init__.py
yby6_crawl_videos_mcp_server-1.0.0.dist-info/METADATA
yby6_crawl_videos_mcp_server-1.0.0.dist-info/WHEEL
yby6_crawl_videos_mcp_server-1.0.0.dist-info/entry_points.txt
yby6_crawl_videos_mcp_server-1.0.0.dist-info/licenses/LICENSE
yby6_crawl_videos_mcp_server-1.0.0.dist-info/RECORD
