Metadata-Version: 2.4
Name: yby6-crawl-videos-mcp-server
Version: 1.0.0
Summary: 全网短视频/图集获取
Project-URL: Homepage, https://yby6.com
Project-URL: Repository, https://github.com/yangbuyiya
Author-email: yangbuyiya <yangbuyiya@duck.com>
License: MIT
License-File: LICENSE
Requires-Python: >=3.10
Requires-Dist: aiofiles>=23.2.1
Requires-Dist: annotated-types>=0.6.0
Requires-Dist: anyio>=4.5
Requires-Dist: certifi>=2024.2.2
Requires-Dist: click>=8.1.7
Requires-Dist: colorama>=0.4.6
Requires-Dist: cssselect>=1.2.0
Requires-Dist: exceptiongroup>=1.2.2
Requires-Dist: fake-useragent>=1.5.1
Requires-Dist: faker>=24.4.0
Requires-Dist: fastapi>=0.110.1
Requires-Dist: fastmcp>=2.10.2
Requires-Dist: h11>=0.14.0
Requires-Dist: httpcore>=1.0.5
Requires-Dist: httptools>=0.6.1
Requires-Dist: httpx>=0.28.1
Requires-Dist: idna>=3.6
Requires-Dist: jinja2>=3.1.3
Requires-Dist: jmespath>=1.0.1
Requires-Dist: lxml>=5.2.1
Requires-Dist: markdown-it-py>=3.0.0
Requires-Dist: markupsafe>=2.1.5
Requires-Dist: mdurl>=0.1.2
Requires-Dist: parsel>=1.9.0
Requires-Dist: pydantic>=2.11.7
Requires-Dist: pygments>=2.17.2
Requires-Dist: pyjwt>=2.8.0
Requires-Dist: python-dateutil>=2.9.0.post0
Requires-Dist: python-dotenv>=1.1.0
Requires-Dist: pyyaml>=6.0.1
Requires-Dist: rich>=13.9.4
Requires-Dist: shellingham>=1.5.4
Requires-Dist: six>=1.16.0
Requires-Dist: sniffio>=1.3.1
Requires-Dist: starlette>=0.37.2
Requires-Dist: typer>=0.15.2
Requires-Dist: uvicorn>=0.29.0
Requires-Dist: w3lib>=2.1.2
Requires-Dist: watchfiles>=0.21.0
Requires-Dist: websockets>=12.0
